{"name":"Rocka0 : An ace programmer","tagline":"","body":"This is Rocka0's homepage.\r\n\r\nHere is a list of projects he has made :\r\n\r\n<ol>\r\n      <li><a href=\"http://rocka0.github.io/solar-system\">Solar-system</a></li>\r\n      <li><a href=\"http://rocka0.github.io/planet-weight\">Weight on other planets</a></li>\r\n      <li><a href=\"http://rocka0.github.io/Js-Sudoko-Solver/\">Javascript Sudoku Solver</a></li>\r\n      <li><a href=\"http://rocka0.github.io/ace_editor\">Html editor online</a></li>\r\n</ol>\r\n    \r\n<h2>To view my blog, click the link below</h2>\r\n<a href=\"http://rocka0.github.io/my_blog\">Blog</a>\r\n","google":"","note":"Don't delete this file! It's used internally to help with page regeneration."}